README.md
setup.py
st.stac.egg-info/PKG-INFO
st.stac.egg-info/SOURCES.txt
st.stac.egg-info/dependency_links.txt
st.stac.egg-info/not-zip-safe
st.stac.egg-info/requires.txt
st.stac.egg-info/top_level.txt
st/stac/__init__.py
st/stac/client.py
st/stac/raster.py
test/test_client.py